pytrilium/PyTrilium.py
pytrilium/PyTriliumAttachmentClient.py
pytrilium/PyTriliumAttributeClient.py
pytrilium/PyTriliumBranchClient.py
pytrilium/PyTriliumCalendarClient.py
pytrilium/PyTriliumClient.py
pytrilium/PyTriliumCustomClient.py
pytrilium/PyTriliumNoteClient.py
pytrilium/__init__.py
pytrilium/log.py
pytrilium-1.3.5.dist-info/METADATA
pytrilium-1.3.5.dist-info/WHEEL
pytrilium-1.3.5.dist-info/licenses/LICENSE
pytrilium-1.3.5.dist-info/RECORD
