Metadata-Version: 2.4
Name: PyTrilium
Version: 1.3.5
Summary: A Python wrapper for the Trilium Notes API
Project-URL: Homepage, https://github.com/perfectra1n/pytrilium
Project-URL: Bug Tracker, https://github.com/perfectra1n/pytrilium/issues
Project-URL: Repository, https://github.com/perfectra1n/pytrilium
Project-URL: Documentation, https://github.com/perfectra1n/pytrilium#readme
Project-URL: Changelog, https://github.com/perfectra1n/pytrilium/releases
Author-email: perfectra1n <perf3ctsec@gmail.com>
License-File: LICENSE
Classifier: License :: OSI Approved :: MIT License
Classifier: Operating System :: OS Independent
Classifier: Programming Language :: Python :: 3
Classifier: Programming Language :: Python :: 3.9
Classifier: Programming Language :: Python :: 3.10
Classifier: Programming Language :: Python :: 3.11
Classifier: Programming Language :: Python :: 3.12
Classifier: Programming Language :: Python :: 3.13
Requires-Python: >=3.9
Requires-Dist: coloredlogs
Requires-Dist: importlib-metadata>=1.0; python_version < '3.8'
Requires-Dist: requests
Provides-Extra: dev
Requires-Dist: black; extra == 'dev'
Requires-Dist: build; extra == 'dev'
Requires-Dist: flake8; extra == 'dev'
Requires-Dist: isort; extra == 'dev'
Requires-Dist: pytest; extra == 'dev'
Requires-Dist: twine; extra == 'dev'
